dave/__init__.py
dave/__main__.py
dave/assets/.gdbinit
dave/assets/.lldbinit
dave/assets/dave
dave/assets/dave_logo_v6.png
dave/assets/lldb_init.py
dave/client/__init__.py
dave/client/__main__.py
dave/client/global_settings.py
dave/client/gui.py
dave/client/in_scope_dict.py
dave/client/settings_tab.py
dave/client/side_panel.py
dave/client/tooltip.py
dave/client/views_tab.py
dave/client/container/__init__.py
dave/client/container/container_model.py
dave/client/container/container_settings_frames.py
dave/client/container/container_side_panel_info.py
dave/client/container/container_views.py
dave/client/container/raw_to_numpy.py
dave/client/entity/__init__.py
dave/client/entity/entity_model.py
dave/client/entity/entity_settings_frame.py
dave/client/entity/entity_side_panel_info.py
dave/client/entity/entity_view.py
dave/client/entity/model_factory.py
dave/client/entity/raw_to_numpy.py
dave/client/iir/__init__.py
dave/client/iir/iir_model.py
dave/client/iir/iir_settings_frame.py
dave/client/iir/iir_side_panel_info.py
dave/client/iir/iir_views.py
dave/client/iir/raw_to_numpy.py
dave/common/__init__.py
dave/common/logger.py
dave/common/raw_container.py
dave/common/raw_entity.py
dave/common/raw_iir.py
dave/common/sample_type.py
dave/common/server_type.py
dave/common/singleton.py
dave/server/__init__.py
dave/server/container.py
dave/server/entity.py
dave/server/entity_factory.py
dave/server/future_gdb.py
dave/server/iir.py
dave/server/process.py
dave/server/debuggers/__init__.py
dave/server/debuggers/command_parsers.py
dave/server/debuggers/value.py
dave/server/debuggers/gdb_/__init__.py
dave/server/debuggers/gdb_/commands.py
dave/server/debuggers/gdb_/formatters.py
dave/server/debuggers/gdb_/value.py
dave/server/debuggers/lldb_/__init__.py
dave/server/debuggers/lldb_/commands.py
dave/server/debuggers/lldb_/formatters.py
dave/server/debuggers/lldb_/value.py
dave/server/debuggers/pdb/__init__.py
dave/server/debuggers/pdb/commands.py
dave/server/debuggers/pdb/value.py
davext-0.12.0.dist-info/licenses/LICENSE
davext-0.12.0.dist-info/METADATA
davext-0.12.0.dist-info/WHEEL
davext-0.12.0.dist-info/top_level.txt
davext-0.12.0.dist-info/RECORD
