Metadata-Version: 2.4
Name: davext
Version: 0.12.0
Summary: base module for the DAVE debugger extension
Home-page: https://github.com/maxmarsc/dave
Author: maxmarsc
Author-email: maxime.coutant@protonmail.com
License: GPLV3
Classifier: Development Status :: 3 - Alpha
Classifier: Intended Audience :: Science/Research
Classifier: Intended Audience :: Developers
Classifier: License :: OSI Approved :: GNU General Public License v3 (GPLv3)
Classifier: Programming Language :: Python :: 3
Classifier: Topic :: Multimedia :: Sound/Audio
Classifier: Topic :: Software Development :: Debuggers
Requires-Python: >3.10.1
License-File: LICENSE
Requires-Dist: PySide6==6.9.0
Requires-Dist: scipy==1.15.2
Requires-Dist: pyqtgraph==0.13.7
Dynamic: author
Dynamic: author-email
Dynamic: classifier
Dynamic: description
Dynamic: description-content-type
Dynamic: home-page
Dynamic: license
Dynamic: license-file
Dynamic: requires-dist
Dynamic: requires-python
Dynamic: summary
